{
    "name": "AncStore",
    "subtitle": "한국어 AltStore 저장소",
    "description": "더 많은 저장소를 추가할 수 있습니다.",
    "iconURL": "https://user-images.githubusercontent.com/705880/65270980-1eb96f80-dad1-11e9-9367-78ccd25ceb02.png",
    "headerURL": "https://user-images.githubusercontent.com/705880/65270980-1eb96f80-dad1-11e9-9367-78ccd25ceb02.png",
    "tintColor": "#018084",
    "featuredApps": [
        "com.ancalina.AltStore"
    ],
    "apps": [
        {
            "name": "알트스토어",
            "bundleIdentifier": "com.ancalina.AltStore",
            "developerName": "ancalina.taekyung",
            "subtitle": "한국어로 번역된 알트스토어",
            "localizedDescription": " ",
            "iconURL": "https://user-images.githubusercontent.com/705880/65270980-1eb96f80-dad1-11e9-9367-78ccd25ceb02.png",
            "tintColor": "#018084",
            "screenshots": [
                "https://raw.githubusercontent.com/ancalina/altkrSource/main/AltStore/1.PNG",
                "https://raw.githubusercontent.com/ancalina/altkrSource/main/AltStore/2.PNG",
                "https://raw.githubusercontent.com/ancalina/altkrSource/main/AltStore/3.PNG",
                "https://raw.githubusercontent.com/ancalina/altkrSource/main/AltStore/4.PNG",
                "https://raw.githubusercontent.com/ancalina/altkrSource/main/AltStore/5.PNG",
                "https://raw.githubusercontent.com/ancalina/altkrSource/main/AltStore/6.PNG",
                {
                    "imageURL": "https://raw.githubusercontent.com/ancalina/altkrSource/main/AltStore/1.PNG",
                    "width": 2556,
                    "height": 1179
                }
            ],
            "versions": [
                                {
                    "version": "2.0b7K",
                    "date": "2024-01-03T17:00:00-00:00",
                    "downloadURL": "https://github.com/ancalina/AltStore/releases/download/latest/AltStore.ipa",
                    "size": 6173806,
                    "localizedDescription": "오류를 수정하고, 번역을 수정했습니다.",
                    "minOSVersion": "14.0"
                },
                {
                    "version": "2.0b6K",
                    "date": "2023-12-31T09:00:00-00:00",
                    "downloadURL": "https://github.com/ancalina/altkrSource/raw/main/ipa%20archive/AltStore%202.0b6K.ipa",
                    "size": 6173708,
                    "localizedDescription": "한국어로 번역되었습니다.",
                    "minOSVersion": "14.0"
                }
            ],
      "permissions": [
        {
          "type": "background-fetch",
          "usageDescription": "알트스토어는 앱이 만료되는 것을 방지하기 위해 주기적으로 앱을 백그라운드에서 새로 고칩니다."
        },
        {
          "type": "background-audio",
          "usageDescription": "앱을 백그라운드에서 새로 고칠 때 알트스토어가 30초 이상 실행되도록 허용합니다."
        }
      ],
      "appPermissions": {
        "entitlements": [
          {
            "name": "get-task-allow"
          },
          {
            "name": "com.apple.security.application-groups"
          },
          {
            "name": "aps-environment"
          },
          {
            "name": "com.apple.developer.siri"
          }
        ],
        "privacy": [
          {
            "name": "LocalNetwork",
            "usageDescription": "알트스토어는 AltServer를 찾고 통신하기위해 로컬 네트워크를 사용합니다."
          }
        ]
      }
        }
    ],
    "news": [
        {
            "title": "한국어로 번역된 알트스토어",
            "identifier": "new_feature",
            "caption": "업데이트는 계속됩니다.",
            "date": "2024-01-01",
            "tintColor": "#5CA399",
            "notify": true
        },
                {
            "title": "2.0b7K 업데이트",
            "identifier": "new_feature",
            "caption": "이 알림을 눌러 설치하세요.",
            "date": "2024-01-01",
            "tintColor": "#5CA399",
            "appID": "com.ancalina.AltStore",
            "notify": true
        }
    ]
}
